pa_license_check/__init__.py
pa_license_check/cli.py
pa_license_check/license_check.py
pa_license_check-0.1.1.dist-info/entry_points.txt
pa_license_check-0.1.1.dist-info/WHEEL
pa_license_check-0.1.1.dist-info/METADATA
pa_license_check-0.1.1.dist-info/RECORD
