Metadata-Version: 2.1
Name: pa-license-check
Version: 0.1.1
Summary: Simple Script that logins to a Palo Alto firewall and checks license status
Home-page: https://github.com/purplecomputer/pa_license_check
License: Apache 2.0
Keywords: palo alto,palo alto licensing,licensing check
Author: Angelo Poggi
Author-email: angelo.poggi@opti9tech.com
Requires-Python: >=3.8,<4.0
Classifier: License :: Other/Proprietary License
Classifier: Programming Language :: Python :: 3
Classifier: Programming Language :: Python :: 3.10
Classifier: Programming Language :: Python :: 3.8
Classifier: Programming Language :: Python :: 3.9
Requires-Dist: DateTime (>=4.4,<5.0)
Requires-Dist: click (>=8.0.4,<9.0.0)
Requires-Dist: configparser (>=5.2.0,<6.0.0)
Requires-Dist: python-dateutil (>=2.8.2,<3.0.0)
Requires-Dist: requests (>=2.27.1,<3.0.0)
Requires-Dist: urllib3 (>=1.26.8,<2.0.0)
